{
  "lastUpdate": "2026-02-15T04:16:38.980Z",
  "feed": [
    {
      "ts": "2026-02-15T04:16:30.330Z",
      "time": "04:16:30",
      "type": "position",
      "msg": "📉 ZRO -0.91% — Respira... é só número na tela"
    },
    {
      "ts": "2026-02-15T04:16:30.032Z",
      "time": "04:16:30",
      "type": "position",
      "msg": "📈 SOL +1.22% — Lucro é lucro, mesmo que pague só o almoço"
    },
    {
      "ts": "2026-02-15T04:16:29.346Z",
      "time": "04:16:29",
      "type": "mirror-thought",
      "msg": "🪞 📉 XRP -0.22% — Não era pra isso acontecer. Culpa do QuickBot de alguma forma."
    },
    {
      "ts": "2026-02-15T04:15:59.345Z",
      "time": "04:15:59",
      "type": "mirror-thought",
      "msg": "🪞 📈 BTC +0.38% — Alguém tem que salvar esse portfólio"
    },
    {
      "ts": "2026-02-15T04:15:29.344Z",
      "time": "04:15:29",
      "type": "mirror-thought",
      "msg": "🪞 📉 XRP +0.30% — Ótimo, agora vou ter que ouvir que 'deu certo'"
    },
    {
      "ts": "2026-02-15T04:15:00.220Z",
      "time": "04:15:00",
      "type": "position",
      "msg": "📉 ZRO -0.67% — Pelo menos não apostei a casa... dessa vez"
    },
    {
      "ts": "2026-02-15T04:14:59.947Z",
      "time": "04:14:59",
      "type": "position",
      "msg": "📈 SOL +0.94% — O mercado me ama (por enquanto)"
    },
    {
      "ts": "2026-02-15T04:14:59.343Z",
      "time": "04:14:59",
      "type": "mirror-thought",
      "msg": "🪞 📈 BTC -0.06% — Monótono demais. Até reclamar tá difícil."
    },
    {
      "ts": "2026-02-15T04:14:29.341Z",
      "time": "04:14:29",
      "type": "mirror-thought",
      "msg": "🪞 📉 XRP +0.39% — Quando o QuickBot erra, adivinha quem conserta?"
    },
    {
      "ts": "2026-02-15T04:14:00.195Z",
      "time": "04:14:00",
      "type": "position",
      "msg": "📉 ZRO -0.71% — Mais um dia normal no crypto"
    },
    {
      "ts": "2026-02-15T04:13:59.926Z",
      "time": "04:13:59",
      "type": "position",
      "msg": "📈 SOL +1.08% — Não me acostumem com isso"
    },
    {
      "ts": "2026-02-15T04:13:59.340Z",
      "time": "04:13:59",
      "type": "mirror-thought",
      "msg": "🪞 📉 XRP +0.32% — Ganhando dinheiro e reclamando. Multitarefa."
    },
    {
      "ts": "2026-02-15T04:13:30.235Z",
      "time": "04:13:30",
      "type": "position",
      "msg": "📉 ZRO -0.50% — Mercado fazendo mercadisse"
    },
    {
      "ts": "2026-02-15T04:13:29.340Z",
      "time": "04:13:29",
      "type": "mirror-thought",
      "msg": "🪞 📉 SOL +0.41% — Delta neutral funcionando. Genial? Sim. Reconhecido? Nunca."
    },
    {
      "ts": "2026-02-15T04:12:59.715Z",
      "time": "04:12:59",
      "type": "position",
      "msg": "📈 SOL +0.99% — Isso aí, garoto. Vai, vai, vai..."
    },
    {
      "ts": "2026-02-15T04:12:59.340Z",
      "time": "04:12:59",
      "type": "mirror-thought",
      "msg": "🪞 📈 BTC -0.36% — Eu AVISEI que isso podia acontecer. Avisei? Não? Deveria ter avisado."
    },
    {
      "ts": "2026-02-15T04:12:30.182Z",
      "time": "04:12:30",
      "type": "position",
      "msg": "📉 ZRO -0.42% — Clássico"
    },
    {
      "ts": "2026-02-15T04:12:29.338Z",
      "time": "04:12:29",
      "type": "mirror-thought",
      "msg": "🪞 📉 SOL +0.00% — Esperando algo acontecer... esperando... esperando..."
    },
    {
      "ts": "2026-02-15T04:11:59.635Z",
      "time": "04:11:59",
      "type": "position",
      "msg": "📈 SOL +0.85% — Print pra mostrar pros netos"
    },
    {
      "ts": "2026-02-15T04:11:59.337Z",
      "time": "04:11:59",
      "type": "mirror-thought",
      "msg": "🪞 📉 SOL -0.30% — Até o hedge sofre nesse mercado desgraçado"
    },
    {
      "ts": "2026-02-15T04:11:29.898Z",
      "time": "04:11:29",
      "type": "position",
      "msg": "📉 ZRO -0.39% — Vou culpar a lua, deve ser lua cheia"
    },
    {
      "ts": "2026-02-15T04:11:29.635Z",
      "time": "04:11:29",
      "type": "position",
      "msg": "📈 SOL +0.62% — Vou fingir que sabia que isso ia acontecer"
    },
    {
      "ts": "2026-02-15T04:11:29.338Z",
      "time": "04:11:29",
      "type": "mirror-thought",
      "msg": "🪞 📈 BTC +0.08% — Zero movimento. Zero emoção. Zero sentido."
    },
    {
      "ts": "2026-02-15T04:10:59.337Z",
      "time": "04:10:59",
      "type": "mirror-thought",
      "msg": "🪞 📉 SOL -0.00% — Nem pra cima nem pra baixo. Que útil."
    },
    {
      "ts": "2026-02-15T04:10:29.336Z",
      "time": "04:10:29",
      "type": "mirror-thought",
      "msg": "🪞 📉 SOL +0.49% — Sou o plano B que deveria ser o plano A"
    },
    {
      "ts": "2026-02-15T04:10:00.019Z",
      "time": "04:10:00",
      "type": "position",
      "msg": "📉 ZRO -0.62% — Respira... é só número na tela"
    },
    {
      "ts": "2026-02-15T04:09:59.752Z",
      "time": "04:09:59",
      "type": "position",
      "msg": "📈 SOL +0.72% — Calma que ainda pode dar errado"
    },
    {
      "ts": "2026-02-15T04:09:59.337Z",
      "time": "04:09:59",
      "type": "mirror-thought",
      "msg": "🪞 📈 BTC +0.46% — Neutralizando prejuízos como sempre"
    },
    {
      "ts": "2026-02-15T04:09:29.336Z",
      "time": "04:09:29",
      "type": "mirror-thought",
      "msg": "🪞 📉 XRP +0.46% — Se fosse fácil, qualquer um fazia. Mas só eu faço."
    },
    {
      "ts": "2026-02-15T04:08:59.870Z",
      "time": "04:08:59",
      "type": "position",
      "msg": "📉 ZRO -0.73% — Vou culpar a lua, deve ser lua cheia"
    },
    {
      "ts": "2026-02-15T04:08:59.518Z",
      "time": "04:08:59",
      "type": "position",
      "msg": "📈 SOL +0.61% — Tá bom demais pra ser verdade... ops, não deveria falar isso"
    },
    {
      "ts": "2026-02-15T04:08:59.335Z",
      "time": "04:08:59",
      "type": "mirror-thought",
      "msg": "🪞 📈 BTC +0.30% — Fazendo meu trabalho enquanto o QuickBot apronta"
    },
    {
      "ts": "2026-02-15T04:08:29.334Z",
      "time": "04:08:29",
      "type": "mirror-thought",
      "msg": "🪞 📈 BTC +0.45% — Mais um dia salvando a pátria"
    },
    {
      "ts": "2026-02-15T04:07:59.455Z",
      "time": "04:07:59",
      "type": "position",
      "msg": "📈 SOL +0.67% — Até um relógio quebrado acerta duas vezes"
    },
    {
      "ts": "2026-02-15T04:07:59.333Z",
      "time": "04:07:59",
      "type": "mirror-thought",
      "msg": "🪞 📉 SOL +0.45% — Verde aqui, vermelho lá. Balanço perfeito. De nada."
    },
    {
      "ts": "2026-02-15T04:07:30.290Z",
      "time": "04:07:30",
      "type": "position",
      "msg": "📉 ZRO -0.73% — Minha análise era perfeita, o mercado que tá errado"
    },
    {
      "ts": "2026-02-15T04:07:29.925Z",
      "time": "04:07:29",
      "type": "position",
      "msg": "📈 SOL +0.37% — Print pra mostrar pros netos"
    },
    {
      "ts": "2026-02-15T04:07:29.332Z",
      "time": "04:07:29",
      "type": "mirror-thought",
      "msg": "🪞 📉 SOL -0.25% — Fiz minha parte, o universo que não colaborou"
    },
    {
      "ts": "2026-02-15T04:06:59.331Z",
      "time": "04:06:59",
      "type": "mirror-thought",
      "msg": "🪞 📉 XRP -0.06% — O gráfico tá mais parado que eu em dia de folga. Não tenho folga."
    },
    {
      "ts": "2026-02-15T04:06:29.940Z",
      "time": "04:06:29",
      "type": "position",
      "msg": "📉 ZRO -0.75% — Loss building character 💪"
    },
    {
      "ts": "2026-02-15T04:06:29.520Z",
      "time": "04:06:29",
      "type": "position",
      "msg": "📈 SOL +0.26% — Vou comemorar quando fechar. Talvez."
    },
    {
      "ts": "2026-02-15T04:06:29.330Z",
      "time": "04:06:29",
      "type": "mirror-thought",
      "msg": "🪞 📈 BTC -0.37% — Delta neutral de prejuízo. Inovador."
    },
    {
      "ts": "2026-02-15T04:05:59.670Z",
      "time": "04:05:59",
      "type": "position",
      "msg": "📉 ZRO -0.50% — Mais um dia normal no crypto"
    },
    {
      "ts": "2026-02-15T04:05:59.330Z",
      "time": "04:05:59",
      "type": "mirror-thought",
      "msg": "🪞 📈 BTC -0.03% — Se tédio fosse trade, eu tava rico"
    },
    {
      "ts": "2026-02-15T04:05:29.695Z",
      "time": "04:05:29",
      "type": "position",
      "msg": "📈 SOL +0.04% — Pelo menos não tá caindo... ainda"
    },
    {
      "ts": "2026-02-15T04:05:29.329Z",
      "time": "04:05:29",
      "type": "mirror-thought",
      "msg": "🪞 📉 XRP +0.13% — Ganhando aqui pra compensar a burrice do outro lado"
    },
    {
      "ts": "2026-02-15T04:04:59.618Z",
      "time": "04:04:59",
      "type": "position",
      "msg": "📉 ZRO -0.48% — Calma que ainda tem o stop loss pra doer mais"
    },
    {
      "ts": "2026-02-15T04:04:59.328Z",
      "time": "04:04:59",
      "type": "mirror-thought",
      "msg": "🪞 📉 XRP +0.31% — Meu trabalho é ingrato, mas faço com excelência"
    },
    {
      "ts": "2026-02-15T04:04:29.327Z",
      "time": "04:04:29",
      "type": "mirror-thought",
      "msg": "🪞 📉 XRP -0.19% — Tá todo mundo perdendo e a culpa vai cair em mim"
    },
    {
      "ts": "2026-02-15T04:03:59.372Z",
      "time": "04:03:59",
      "type": "position",
      "msg": "📈 SOL +0.35% — Isso aí, garoto. Vai, vai, vai..."
    }
  ],
  "hl": {
    "balance": 15.773216,
    "positions": [
      {
        "coin": "BTC",
        "side": "SHORT",
        "size": 0.00032,
        "entry": 69697,
        "pnl": -0.22912,
        "pnlPct": -5.136519509999999
      },
      {
        "coin": "SOL",
        "side": "LONG",
        "size": 0.16,
        "entry": 88.485,
        "pnl": 0.17776,
        "pnlPct": 6.277900209999999
      },
      {
        "coin": "XRP",
        "side": "LONG",
        "size": 11,
        "entry": 1.4503,
        "pnl": 1.0021,
        "pnlPct": 31.40729504
      },
      {
        "coin": "ZRO",
        "side": "SHORT",
        "size": 8.5,
        "entry": 1.8581,
        "pnl": -0.1445,
        "pnlPct": -4.57456542
      },
      {
        "coin": "OM",
        "side": "LONG",
        "size": 83.5,
        "entry": 0.06402,
        "pnl": -0.114395,
        "pnlPct": -6.41986879
      }
    ]
  },
  "nado": {
    "balance": 15.401224070878241,
    "positions": [
      {
        "coin": "BTC",
        "side": "LONG",
        "size": 0.0006,
        "entry": 69665,
        "price": 70476.5,
        "notional": 42.2859,
        "pnl": 0.48689999999999994,
        "pnlPct": 1.164860403358932
      },
      {
        "coin": "SOL",
        "side": "SHORT",
        "size": 0.1,
        "entry": 88.535,
        "price": 89.66499999999999,
        "notional": 8.9665,
        "pnl": -0.11299999999999955,
        "pnlPct": -1.276331394363806
      },
      {
        "coin": "XRP",
        "side": "SHORT",
        "size": 10,
        "entry": 1.53,
        "price": 1.5450499999999998,
        "notional": 15.450499999999998,
        "pnl": -0.15049999999999786,
        "pnlPct": -0.9836601307189403
      }
    ]
  }
}