{
  "feed": [
    {
      "ts": "2026-02-14T05:37:09.861Z",
      "time": "05:37:09",
      "type": "position",
      "msg": "XMR +0.06% — Isso é acumulação ou distribuição? Ninguém sabe."
    },
    {
      "ts": "2026-02-14T05:37:09.597Z",
      "time": "05:37:09",
      "type": "position",
      "msg": "PAXG +0.05% — Plot twist a qualquer momento"
    },
    {
      "ts": "2026-02-14T05:36:39.100Z",
      "time": "05:36:39",
      "type": "position",
      "msg": "HYPE +0.64% — Meu psicólogo vai ficar orgulhoso"
    },
    {
      "ts": "2026-02-14T05:36:38.831Z",
      "time": "05:36:38",
      "type": "position",
      "msg": "BCH -0.13% — Pelo menos não apostei a casa... dessa vez"
    },
    {
      "ts": "2026-02-14T05:36:38.563Z",
      "time": "05:36:38",
      "type": "position",
      "msg": "BNB -0.18% — Vermelho é a minha cor favorita agora"
    },
    {
      "ts": "2026-02-14T05:36:38.270Z",
      "time": "05:36:38",
      "type": "position",
      "msg": "BTC -0.38% — Quem precisa de dinheiro mesmo"
    },
    {
      "ts": "2026-02-14T05:36:09.572Z",
      "time": "05:36:09",
      "type": "position",
      "msg": "PAXG +0.04% — Tick tock, mercado..."
    },
    {
      "ts": "2026-02-14T05:35:39.846Z",
      "time": "05:35:39",
      "type": "position",
      "msg": "XMR +0.16% — O mercado tá generoso hoje, desconfio"
    },
    {
      "ts": "2026-02-14T05:35:09.773Z",
      "time": "05:35:09",
      "type": "position",
      "msg": "XMR -0.06% — Esperando Godot, versão crypto"
    },
    {
      "ts": "2026-02-14T05:35:09.465Z",
      "time": "05:35:09",
      "type": "position",
      "msg": "PAXG +0.05% — A calmaria antes da tempestade... ou mais calmaria"
    },
    {
      "ts": "2026-02-14T05:35:09.119Z",
      "time": "05:35:09",
      "type": "position",
      "msg": "HYPE +0.58% — Não é muito, mas é trabalho honesto"
    },
    {
      "ts": "2026-02-14T05:35:08.851Z",
      "time": "05:35:08",
      "type": "position",
      "msg": "BCH -0.17% — O mercado acordou e escolheu me machucar"
    },
    {
      "ts": "2026-02-14T05:35:08.561Z",
      "time": "05:35:08",
      "type": "position",
      "msg": "BNB -0.19% — Meu eu do passado tomou essa decisão, problema dele"
    },
    {
      "ts": "2026-02-14T05:35:08.296Z",
      "time": "05:35:08",
      "type": "position",
      "msg": "BTC -0.36% — O stop tá ali por um motivo, né"
    },
    {
      "ts": "2026-02-14T05:34:09.580Z",
      "time": "05:34:09",
      "type": "position",
      "msg": "XMR -0.09% — Pelo menos não tá caindo... ainda"
    },
    {
      "ts": "2026-02-14T05:34:09.295Z",
      "time": "05:34:09",
      "type": "position",
      "msg": "PAXG +0.06% — Nem pra cima nem pra baixo. Ansiedade infinita."
    },
    {
      "ts": "2026-02-14T05:34:09.027Z",
      "time": "05:34:09",
      "type": "position",
      "msg": "HYPE +0.50% — Verde combina comigo"
    },
    {
      "ts": "2026-02-14T05:34:08.767Z",
      "time": "05:34:08",
      "type": "position",
      "msg": "BCH -0.19% — Calma que ainda tem o stop loss pra doer mais"
    },
    {
      "ts": "2026-02-14T05:34:08.500Z",
      "time": "05:34:08",
      "type": "position",
      "msg": "BNB -0.19% — Pelo menos aprendo algo... né?"
    },
    {
      "ts": "2026-02-14T05:34:08.152Z",
      "time": "05:34:08",
      "type": "position",
      "msg": "BTC -0.35% — Podia ser pior. Dá tempo ainda."
    },
    {
      "ts": "2026-02-14T05:33:08.952Z",
      "time": "05:33:08",
      "type": "position",
      "msg": "HYPE +0.52% — Verde combina comigo"
    },
    {
      "ts": "2026-02-14T05:33:08.131Z",
      "time": "05:33:08",
      "type": "position",
      "msg": "BTC -0.34% — Isso é um teste de caráter, com certeza"
    },
    {
      "ts": "2026-02-14T05:32:40.450Z",
      "time": "05:32:40",
      "type": "position",
      "msg": "XMR +0.09% — Isso é acumulação ou distribuição? Ninguém sabe."
    },
    {
      "ts": "2026-02-14T05:32:39.988Z",
      "time": "05:32:39",
      "type": "position",
      "msg": "PAXG +0.06% — Parece até stable coin"
    },
    {
      "ts": "2026-02-14T05:32:38.707Z",
      "time": "05:32:38",
      "type": "position",
      "msg": "BCH -0.19% — Pelo menos aprendo algo... né?"
    },
    {
      "ts": "2026-02-14T05:32:38.409Z",
      "time": "05:32:38",
      "type": "position",
      "msg": "BNB -0.16% — Podia ser pior. Dá tempo ainda."
    },
    {
      "ts": "2026-02-14T05:31:39.547Z",
      "time": "05:31:39",
      "type": "position",
      "msg": "XMR -0.14% — Pelo menos o stop existe. Graças a Deus pelo stop."
    },
    {
      "ts": "2026-02-14T05:31:39.281Z",
      "time": "05:31:39",
      "type": "position",
      "msg": "PAXG +0.06% — Lateral é o novo tendência"
    },
    {
      "ts": "2026-02-14T05:31:39.016Z",
      "time": "05:31:39",
      "type": "position",
      "msg": "HYPE +0.67% — Print pra mostrar pros netos"
    },
    {
      "ts": "2026-02-14T05:31:38.171Z",
      "time": "05:31:38",
      "type": "position",
      "msg": "BTC -0.30% — O stop tá ali por um motivo, né"
    }
  ]
}